{
	"autoCrudStr": "F",
	"cobisPattern": "None",
	"cobisPatternId": 0,
	"commands": [
	],
	"customEvents": [
	],
	"customizationLayer": 0,
	"customizationLayerDescription": "ECU",
	"graphicSupportStr": "F",
	"header": null,
	"id": {
		"moduleId": "INTRD",
		"subModuleId": "FRMLR",
		"taskId": "T_INTRDKAXJGOVP_212",
		"version": "1.0.0"
	},
	"isCustomized": false,
	"isImported": false,
	"mainViewContainerId": "VC_EVENTOSCTL_762212",
	"modeEnabled": 4095,
	"name": {
		"$ref": "../../../../INTRD/relations/componentKeys.json#/FRMLR/Forms/T_INTRDKAXJGOVP_212/name"
	},
	"setFocus": false,
	"tempSaveStr": "F",
	"viewContainers": [
		{
			"breadcrumbs": "Automatic",
			"collapsedStr": "F",
			"colSpan": 1,
			"columnsNum": 1,
			"componentStyle": null,
			"customEvents": [
			],
			"customizationLayer": 0,
			"customizationLayerDescription": "ECU",
			"enabled": 4095,
			"id": {
				"moduleId": "INTRD",
				"subModuleId": "FRMLR",
				"taskId": "T_INTRDKAXJGOVP_212",
				"taskVersion": "1.0.0",
				"viewContainerId": "VC_EVENTOSCTL_762212"
			},
			"isCustomized": false,
			"layoutType": "Group",
			"name": "EventosCliente",
			"options": 0,
			"responsiveLayouts": null,
			"responsivity": false,
			"style": null,
			"view": {
				"groups": [
					{
						"collapsedStr": "F",
						"colSpan": 1,
						"columnsNum": 3,
						"componentStyle": null,
						"customEvents": [
						],
						"enabled": 4095,
						"entity": {
							"$ref": "../../../../INTRD/entities/EN_PERSONAMG_670.json#"
						},
						"eventType": 0,
						"groupId": "G_EVENTOSEEI_936237",
						"htmlSection": "F",
						"independentValidation": "F",
						"isCustomized": false,
						"layoutType": "Group",
						"name": "Group1472",
						"order": 1,
						"orientation": "V",
						"responsiveLayouts": null,
						"responsivity": false,
						"style": null,
						"visible": 4095,
						"visualAttributes": [
							{
								"aggregate": null,
								"aggregateId": null,
								"attribute": {
									"$ref": "../../../../INTRD/entities/EN_PERSONAMG_670.json#/attributes/AT83_NOMBREZS670"
								},
								"attributeValidations": [
								],
								"colSpan": 1,
								"componentInGrid": false,
								"componentStyle": null,
								"customEvents": [
								],
								"customizationLayer": 0,
								"customizationLayerDescription": "ECU",
								"enabled": 4095,
								"format": "",
								"include": 4095,
								"isCustomized": false,
								"label": {
									"defaultValue": {
										"$ref": "../../../../INTRD/assets/languages/INTRD.json#/INTRD/LBL/LBL_INTRD_NOMBREZHE_51917"
									},
									"labelId": "LBL_INTRD_NOMBREZHE_51917",
									"moduleId": "INTRD"
								},
								"maxRecords": null,
								"name": "nombre",
								"options": 0,
								"order": 1,
								"readOnly": 8,
								"responsiveLayouts": null,
								"responsivity": false,
								"sizeWidthComposite": null,
								"style": null,
								"textRows": 0,
								"userControl": {
									"type": "I",
									"userControlId": "TextInputBox"
								},
								"visible": 4095,
								"visualAttributeId": "VA_1DLVSHEYFIPTZWU_698237",
								"width": null,
								"widthComposite": "D"
							},
							{
								"aggregate": null,
								"aggregateId": null,
								"attribute": {
									"$ref": "../../../../INTRD/entities/EN_PERSONAMG_670.json#/attributes/AT97_NOMBREMO670"
								},
								"attributeValidations": [
								],
								"colSpan": 2,
								"componentInGrid": false,
								"componentStyle": null,
								"customEvents": [
								],
								"customizationLayer": 0,
								"customizationLayerDescription": "ECU",
								"enabled": 4095,
								"format": "",
								"include": 4095,
								"isCustomized": false,
								"label": {
									"defaultValue": {
										"$ref": "../../../../INTRD/assets/languages/INTRD.json#/INTRD/LBL/LBL_INTRD_NOMBRECPM_47454"
									},
									"labelId": "LBL_INTRD_NOMBRECPM_47454",
									"moduleId": "INTRD"
								},
								"maxRecords": null,
								"name": "nombreCompleto",
								"options": 0,
								"order": 4,
								"readOnly": 8,
								"responsiveLayouts": null,
								"responsivity": false,
								"sizeWidthComposite": null,
								"style": null,
								"textRows": 0,
								"userControl": {
									"type": "I",
									"userControlId": "TextInputBox"
								},
								"visible": 4095,
								"visualAttributeId": "VA_2822GANLWSFSMWC_473237",
								"width": null,
								"widthComposite": "D"
							},
							{
								"aggregate": null,
								"aggregateId": null,
								"attribute": {
									"$ref": "../../../../INTRD/entities/EN_PERSONAMG_670.json#/attributes/AT24_APELLIOD670"
								},
								"attributeValidations": [
								],
								"colSpan": 1,
								"componentInGrid": false,
								"componentStyle": null,
								"customEvents": [
								],
								"customizationLayer": 0,
								"customizationLayerDescription": "ECU",
								"enabled": 4095,
								"format": "",
								"include": 4095,
								"isCustomized": false,
								"label": {
									"defaultValue": {
										"$ref": "../../../../INTRD/assets/languages/INTRD.json#/INTRD/LBL/LBL_INTRD_APELLIDOO_56272"
									},
									"labelId": "LBL_INTRD_APELLIDOO_56272",
									"moduleId": "INTRD"
								},
								"maxRecords": null,
								"name": "apellido",
								"options": 0,
								"order": 2,
								"readOnly": 8,
								"responsiveLayouts": null,
								"responsivity": false,
								"sizeWidthComposite": null,
								"style": null,
								"textRows": 0,
								"userControl": {
									"type": "I",
									"userControlId": "TextInputBox"
								},
								"visible": 4095,
								"visualAttributeId": "VA_3277ZVVHSHEYCAV_260237",
								"width": null,
								"widthComposite": "D"
							},
							{
								"aggregate": null,
								"aggregateId": null,
								"attributeValidations": [
								],
								"colSpan": 1,
								"componentInGrid": false,
								"componentStyle": null,
								"customEvents": [
									{
										"customEventId": "CEVA_010VA_VABUTTONCJJTCMU_223237_532",
										"customizationLayer": 0,
										"customizationLayerDescription": "ECU",
										"enabled": "T",
										"eventActions": [
										],
										"executionType": 1,
										"filter": null,
										"isEnabled": true,
										"visualAttributeEventType": {
											"availableExecutionType": 7,
											"description": "Permite personalizar la acci\u00f3n a ejecutar de un command o de un ActionControl",
											"eventId": 10,
											"name": "ExecuteCommand"
										}
									}
								],
								"customizationLayer": 0,
								"customizationLayerDescription": "ECU",
								"enabled": 4095,
								"entityQuery": null,
								"include": 4095,
								"isCustomized": false,
								"label": {
									"defaultValue": {
										"$ref": "../../../../INTRD/assets/languages/INTRD.json#/INTRD/LBL/LBL_INTRD_CLEANIQEQ_47709"
									},
									"labelId": "LBL_INTRD_CLEANIQEQ_47709",
									"moduleId": "INTRD"
								},
								"maxRecords": null,
								"name": "VA_VABUTTONCJJTCMU_223237",
								"options": 0,
								"order": 5,
								"queryModule": null,
								"queryVersion": null,
								"responsiveLayouts": null,
								"responsivity": false,
								"sizeWidthComposite": null,
								"style": null,
								"userControl": {
									"type": "A",
									"userControlId": "Button"
								},
								"visible": 4095,
								"visualAttributeId": "VA_VABUTTONCJJTCMU_223237",
								"width": null,
								"widthComposite": "D"
							},
							{
								"aggregate": null,
								"aggregateId": null,
								"attributeValidations": [
								],
								"colSpan": 1,
								"componentInGrid": false,
								"componentStyle": null,
								"customEvents": [
									{
										"customEventId": "CEVA_010VA_VABUTTONTKMQMZH_755237_849",
										"customizationLayer": 0,
										"customizationLayerDescription": "ECU",
										"enabled": "T",
										"eventActions": [
										],
										"executionType": 1,
										"filter": null,
										"isEnabled": true,
										"visualAttributeEventType": {
											"availableExecutionType": 7,
											"description": "Permite personalizar la acci\u00f3n a ejecutar de un command o de un ActionControl",
											"eventId": 10,
											"name": "ExecuteCommand"
										}
									}
								],
								"customizationLayer": 0,
								"customizationLayerDescription": "ECU",
								"enabled": 4095,
								"entityQuery": null,
								"include": 4095,
								"isCustomized": false,
								"label": {
									"defaultValue": {
										"$ref": "../../../../INTRD/assets/languages/INTRD.json#/INTRD/LBL/LBL_INTRD_OKTSQYVNQ_51510"
									},
									"labelId": "LBL_INTRD_OKTSQYVNQ_51510",
									"moduleId": "INTRD"
								},
								"maxRecords": null,
								"name": "VA_VABUTTONTKMQMZH_755237",
								"options": 0,
								"order": 3,
								"queryModule": null,
								"queryVersion": null,
								"responsiveLayouts": null,
								"responsivity": false,
								"sizeWidthComposite": null,
								"style": null,
								"userControl": {
									"type": "A",
									"userControlId": "Button"
								},
								"visible": 4095,
								"visualAttributeId": "VA_VABUTTONTKMQMZH_755237",
								"width": null,
								"widthComposite": "D"
							}
						]
					}
				],
				"id": {
					"version": "1.0.0",
					"viewId": "VW_EVENTOSCEI_237"
				},
				"metadataVersion": "7.2.0.2024 BETA",
				"modules": [
					{
						"moduleId": "INTRD"
					}
				],
				"name": "View of EventosCliente"
			}
		}
	]
}
